{
  "events": [
    {
      "time": "10:00 AM",
      "description": "Wedding Ceremony",
      "image": "/assets/images/graphics/ceremony-2.png",
      "imageAlt": "Wedding Ceremony",
      "position": "left"
    },
    {
      "time": "12:00 PM",
      "description": "Reception Lunch",
      "image": "/assets/images/graphics/dinner-2.png",
      "imageAlt": "Reception Lunch",
      "position": "right"
    },
    {
      "time": "3:00 PM",
      "description": "End",
      "image": "/assets/images/graphics/cake-2.png",
      "imageAlt": "End",
      "position": "left"
    }
  ]
}
